pycphy/__init__.py
pycphy/cli.py
pycphy/config_manager.py
pycphy/foamCaseDeveloper/__init__.py
pycphy/foamCaseDeveloper/develop_case.py
pycphy/foamCaseDeveloper/main.py
pycphy/foamCaseDeveloper/config/__init__.py
pycphy/foamCaseDeveloper/config/cad_mesh_config.py
pycphy/foamCaseDeveloper/config/config_hfdibdem.py
pycphy/foamCaseDeveloper/config/csv_boundary_reader.py
pycphy/foamCaseDeveloper/config/global_config.py
pycphy/foamCaseDeveloper/config/constant/__init__.py
pycphy/foamCaseDeveloper/config/constant/dynamic_mesh_config.py
pycphy/foamCaseDeveloper/config/constant/gravity_field_config.py
pycphy/foamCaseDeveloper/config/constant/transport_properties_config.py
pycphy/foamCaseDeveloper/config/constant/turbulence_config.py
pycphy/foamCaseDeveloper/config/system/__init__.py
pycphy/foamCaseDeveloper/config/system/block_mesh_config.py
pycphy/foamCaseDeveloper/config/system/control_config.py
pycphy/foamCaseDeveloper/config/system/decompose_par_config.py
pycphy/foamCaseDeveloper/config/system/fv_options_config.py
pycphy/foamCaseDeveloper/config/system/fv_schemes_config.py
pycphy/foamCaseDeveloper/config/system/set_fields_config.py
pycphy/foamCaseDeveloper/config/system/snappy_hex_mesh_config.py
pycphy/foamCaseDeveloper/config/zero/U_config.py
pycphy/foamCaseDeveloper/config/zero/__init__.py
pycphy/foamCaseDeveloper/config/zero/f_config.py
pycphy/foamCaseDeveloper/config/zero/lambda_config.py
pycphy/foamCaseDeveloper/config/zero/p_config.py
pycphy/foamCaseDeveloper/core/__init__.py
pycphy/foamCaseDeveloper/core/block_mesh_developer.py
pycphy/foamCaseDeveloper/core/cad_block_mesh_developer.py
pycphy/foamCaseDeveloper/core/case_builder.py
pycphy/foamCaseDeveloper/core/foam_case_manager.py
pycphy/foamCaseDeveloper/utils/myAutoCAD.py
pycphy/foamCaseDeveloper/writers/__init__.py
pycphy/foamCaseDeveloper/writers/foam_writer.py
pycphy/foamCaseDeveloper/writers/constant/__init__.py
pycphy/foamCaseDeveloper/writers/constant/dynamic_mesh_dict_writer.py
pycphy-0.2.0.dist-info/licenses/LICENSE
pycphy-0.2.0.dist-info/METADATA
pycphy-0.2.0.dist-info/WHEEL
pycphy-0.2.0.dist-info/entry_points.txt
pycphy-0.2.0.dist-info/top_level.txt
pycphy-0.2.0.dist-info/RECORD
