Metadata-Version: 2.4
Name: pycphy
Version: 0.2.0
Summary: Python: Computational Physics - Tools for physics dynamics simulation with CAD-based OpenFOAM case generation
Home-page: https://github.com/SanjeevBashyal/pycphy
Author: Sanjeev Bashyal
Author-email: Sanjeev Bashyal <sanjeev.bashyal@example.com>
Maintainer-email: Sanjeev Bashyal <sanjeev.bashyal@example.com>
License: MIT
Project-URL: Homepage, https://github.com/SanjeevBashyal/pycphy
Project-URL: Repository, https://github.com/SanjeevBashyal/pycphy
Project-URL: Documentation, https://github.com/SanjeevBashyal/pycphy#readme
Project-URL: Bug Tracker, https://github.com/SanjeevBashyal/pycphy/issues
Keywords: computational physics,simulation,openfoam,cfd,physics,autocad,cad,mesh generation,blockmesh
Classifier: Development Status :: 3 - Alpha
Classifier: Intended Audience :: Science/Research
Classifier: Operating System :: Microsoft :: Windows
Classifier: Programming Language :: Python :: 3
Classifier: Programming Language :: Python :: 3.7
Classifier: Programming Language :: Python :: 3.8
Classifier: Programming Language :: Python :: 3.9
Classifier: Programming Language :: Python :: 3.10
Classifier: Programming Language :: Python :: 3.11
Classifier: Topic :: Scientific/Engineering :: Physics
Classifier: Topic :: Scientific/Engineering :: Mathematics
Classifier: Topic :: Scientific/Engineering :: Information Analysis
Classifier: Topic :: Software Development :: Libraries :: Python Modules
Requires-Python: >=3.7
License-File: LICENSE
Requires-Dist: numpy>=1.19.0
Requires-Dist: scipy>=1.6.0
Requires-Dist: matplotlib>=3.3.0
Requires-Dist: pandas>=1.3.0
Provides-Extra: dev
Requires-Dist: pytest>=6.0; extra == "dev"
Requires-Dist: pytest-cov; extra == "dev"
Requires-Dist: black; extra == "dev"
Requires-Dist: flake8; extra == "dev"
Requires-Dist: mypy; extra == "dev"
Provides-Extra: docs
Requires-Dist: sphinx; extra == "docs"
Requires-Dist: sphinx-rtd-theme; extra == "docs"
Provides-Extra: cad
Requires-Dist: pyautocad>=0.2.0; extra == "cad"
Requires-Dist: pywin32>=304; extra == "cad"
Provides-Extra: all
Requires-Dist: pyautocad>=0.2.0; extra == "all"
Requires-Dist: pywin32>=304; extra == "all"
Dynamic: author
Dynamic: home-page
Dynamic: license-file
Dynamic: requires-python
